keepthink/__init__.py
keepthink/chat.py
keepthink/cli.py
keepthink/prompts/__init__.py
keepthink/prompts/think_prompt
keepthink/web/__init__.py
keepthink/web/app.py
keepthink/web/static/css/styles.css
keepthink/web/static/js/main.js
keepthink/web/templates/__init__.py
keepthink/web/templates/index.html
keepthink-0.0.13.dist-info/METADATA
keepthink-0.0.13.dist-info/WHEEL
keepthink-0.0.13.dist-info/entry_points.txt
keepthink-0.0.13.dist-info/top_level.txt
keepthink-0.0.13.dist-info/RECORD
